Denis_Ivakhov/__init__.py
Denis_Ivakhov/my_module.py
Denis_Ivakhov-0.0.1.dist-info/METADATA
Denis_Ivakhov-0.0.1.dist-info/WHEEL
Denis_Ivakhov-0.0.1.dist-info/top_level.txt
Denis_Ivakhov-0.0.1.dist-info/RECORD
