Metadata-Version: 2.1
Name: Denis-Ivakhov
Version: 0.0.1
Summary: My simple Python module
Author: Denis Ivakhov
Author-email: d.ivahov2008@gmail.com
Classifier: Programming Language :: Python :: 3
Classifier: License :: OSI Approved :: MIT License
Classifier: Operating System :: OS Independent
Requires-Python: >=3.6
